dashai_deepseek_model_package/__init__.py
dashai_deepseek_model_package/deepseek_model.py
dashai_deepseek_model_package-0.0.6.dist-info/METADATA
dashai_deepseek_model_package-0.0.6.dist-info/WHEEL
dashai_deepseek_model_package-0.0.6.dist-info/entry_points.txt
dashai_deepseek_model_package-0.0.6.dist-info/RECORD
